ogloji/__init__.py
ogloji-0.1.11.dist-info/METADATA
ogloji-0.1.11.dist-info/WHEEL
ogloji-0.1.11.dist-info/entry_points.txt
ogloji-0.1.11.dist-info/licenses/LICENSE
ogloji-0.1.11.dist-info/RECORD
